{
  "recentFiles": [
    {
      "basename": "00. 主页",
      "path": "40 - Obsidian/主页/00. 主页.md"
    },
    {
      "basename": "ABSESpy",
      "path": "Projects/ABSESpy.md"
    },
    {
      "basename": "00. 导航",
      "path": "40 - Obsidian/主页/00. 导航.md"
    },
    {
      "basename": "Decreased virtual water outflows from the Yellow River basin are increasingly critical to China",
      "path": "Inputs/Zotero/Decreased virtual water outflows from the Yellow River basin are increasingly critical to China.md"
    },
    {
      "basename": "Quantifying the effects of institutional shifts on water governance in the Yellow River Basin_ A ",
      "path": "Inputs/Zotero/Quantifying the effects of institutional shifts on water governance in the Yellow River Basin_ A .md"
    },
    {
      "basename": "Identifying Regime Transitions for Water Governance in the Yellow River Basin, China",
      "path": "Inputs/Zotero/Identifying Regime Transitions for Water Governance in the Yellow River Basin, China.md"
    },
    {
      "basename": "Improving representation of collective memory in socio‐hydrological models and new insights into ",
      "path": "Inputs/Zotero/Improving representation of collective memory in socio‐hydrological models and new insights into .md"
    },
    {
      "basename": "关于科研生活的探讨",
      "path": "Outputs/关于科研生活的探讨.md"
    },
    {
      "basename": "zt-field.eta",
      "path": "40 - Obsidian/模板/zt-field.eta.md"
    },
    {
      "basename": "zt-note.eta",
      "path": "40 - Obsidian/模板/zt-note.eta.md"
    },
    {
      "basename": "每周周记模板",
      "path": "40 - Obsidian/模板/每周周记模板.md"
    },
    {
      "basename": "README",
      "path": "README.md"
    },
    {
      "basename": "设计理念",
      "path": "Outputs/设计理念.md"
    },
    {
      "basename": "使用PaperBell整理输出笔记",
      "path": "Outputs/使用PaperBell整理输出笔记.md"
    },
    {
      "basename": "输出笔记模板",
      "path": "40 - Obsidian/模板/输出笔记模板.md"
    },
    {
      "basename": "是否适用于你",
      "path": "Outputs/是否适用于你.md"
    },
    {
      "basename": "数据方法",
      "path": "40 - Obsidian/img/数据方法.png"
    },
    {
      "basename": "结果",
      "path": "40 - Obsidian/img/结果.jpg"
    },
    {
      "basename": "方法",
      "path": "40 - Obsidian/img/方法.jpg"
    },
    {
      "basename": "引言",
      "path": "40 - Obsidian/img/引言.jpg"
    },
    {
      "basename": "阅读论文标注方法",
      "path": "40 - Obsidian/img/阅读论文标注方法.png"
    },
    {
      "basename": "paperbell",
      "path": "40 - Obsidian/img/paperbell.png"
    },
    {
      "basename": "社会—生态系统适应性治理研究进展与展望",
      "path": "Inputs/Zotero/社会—生态系统适应性治理研究进展与展望.md"
    },
    {
      "basename": "追踪项目",
      "path": "40 - Obsidian/附件/追踪项目.gif"
    },
    {
      "basename": "宋爽",
      "path": "Persons/Scholars/宋爽.md"
    },
    {
      "basename": "00. 学者列表",
      "path": "Persons/00. 学者列表.md"
    },
    {
      "basename": "使用PaperBell进行日常记录",
      "path": "Outputs/使用PaperBell进行日常记录.md"
    },
    {
      "basename": "Social ecological system",
      "path": "Cards/Concepts/Social ecological system.md"
    },
    {
      "basename": "00. 机构列表",
      "path": "Locations/00. 机构列表.md"
    },
    {
      "basename": "00. 概念墙",
      "path": "Cards/00. 概念墙.md"
    },
    {
      "basename": "使用PaperBell管理项目",
      "path": "Outputs/使用PaperBell管理项目.md"
    },
    {
      "basename": "agent-based model",
      "path": "Cards/Concepts/agent-based model.md"
    },
    {
      "basename": "使用PaperBell阅读与整理资料",
      "path": "Outputs/使用PaperBell阅读与整理资料.md"
    },
    {
      "basename": "PaperBell",
      "path": "Projects/PaperBell.md"
    },
    {
      "basename": "武旭同",
      "path": "Persons/Scholars/武旭同.md"
    },
    {
      "basename": "Decoupling of SDGs followed by re-coupling as sustainable development progresses",
      "path": "Inputs/Zotero/Decoupling of SDGs followed by re-coupling as sustainable development progresses.md"
    },
    {
      "basename": "学者模板",
      "path": "40 - Obsidian/模板/学者模板.md"
    },
    {
      "basename": "术语模板",
      "path": "40 - Obsidian/模板/术语模板.md"
    },
    {
      "basename": "多主体建模的包",
      "path": "Outputs/多主体建模的包.md"
    },
    {
      "basename": "2024年05月14日",
      "path": "00 - 每日日记/DailyNote/2024年05月14日.md"
    },
    {
      "basename": "项目模板",
      "path": "40 - Obsidian/模板/项目模板.md"
    },
    {
      "basename": "zt-annot.eta",
      "path": "40 - Obsidian/模板/zt-annot.eta.md"
    },
    {
      "basename": "每日日记模板",
      "path": "40 - Obsidian/模板/每日日记模板.md"
    },
    {
      "basename": "2024年05月13日",
      "path": "00 - 每日日记/DailyNote/2024年05月13日.md"
    },
    {
      "basename": "学术哲学的邀请—在学术中，何必恐惧飞翔！ 精选",
      "path": "Inputs/Cubox/学术哲学的邀请—在学术中，何必恐惧飞翔！ 精选.md"
    },
    {
      "basename": "PaperBell仓库使用的插件及其作用一览",
      "path": "Outputs/PaperBell仓库使用的插件及其作用一览.md"
    },
    {
      "basename": "科学革命的结构",
      "path": "40 - Obsidian/附件/科学革命的结构.jpg"
    },
    {
      "basename": "Cotacachi",
      "path": "Locations/Places/Cotacachi.md"
    },
    {
      "basename": "douban_book",
      "path": "40 - Obsidian/模板/douban_book.md"
    },
    {
      "basename": "00. 文件管理",
      "path": "40 - Obsidian/主页/00. 文件管理.md"
    }
  ],
  "omittedPaths": [],
  "maxLength": null,
  "openType": "tab"
}